{
  "resourceType": "ValueSet",
  "id": "emcare-b2-de02",
  "url": "http://fhir.org/guides/who/emc-cds/ValueSet/emcare-b2-de02",
  "name": "emcare-b2-de02",
  "title": "Type of Visit Choices",
  "status": "draft",
  "experimental": false,
  "description": "Codes representing possible values for the Type of Visit Choices element",
  "immutable": true,
  "compose": {
    "include": [ {
      "system": "http://fhir.org/guides/who/emc-cds/CodeSystem/emc-custom-codes",
      "concept": [ {
        "code": "EmCare.B2.DE02",
        "display": "Planned"
      }, {
        "code": "EmCare.B2.DE03",
        "display": "Unplanned"
      } ]
    } ]
  }
}