{
  "resourceType": "StructureDefinition",
  "id": "emcare-device",
  "url": "http://fhir.org/guides/who/emc-cds/StructureDefinition/emcare-device",
  "name": "EmCare Device",
  "title": "EmCare Device",
  "status": "draft",
  "experimental": false,
  "description": "EmCare Device",
  "useContext": [ {
    "code": {
      "system": "http://terminology.hl7.org/CodeSystem/usage-context-type",
      "code": "task",
      "display": "Workflow Task"
    },
    "valueCodeableConcept": {
      "coding": [ {
        "system": "http://fhir.org/guides/who/emc-cds/CodeSystem/activity-codes",
        "code": "EmCare.B6.",
        "display": "Measurements"
      } ]
    }
  } ],
  "fhirVersion": "4.0.1",
  "mapping": [ {
    "identity": "EmCare",
    "uri": "PLACEHOLDER - URI",
    "name": "Digital Adaptation Kit for Emergency Care"
  } ],
  "kind": "resource",
  "abstract": false,
  "type": "Observation",
  "baseDefinition": "http://fhir.org/guides/who/core/StructureDefinition/who-observation",
  "derivation": "constraint",
  "differential": {
    "element": [ {
      "id": "Observation",
      "path": "Observation",
      "mustSupport": false
    }, {
      "id": "Observation.code",
      "path": "Observation.code",
      "short": "Thermometer not available",
      "min": 1,
      "max": "1",
      "mustSupport": true,
      "mapping": [ {
        "identity": "EmCare",
        "map": "EmCare.B6.DE04"
      } ]
    } ]
  }
}