[
  {
    "id": "who-allergyintolerance",
    "type": "StructureDefinition",
    "url": "http://fhir.org/guides/who/core/StructureDefinition/who-allergyintolerance",
    "version": "0.1.0",
    "name": "WHOAllergyIntolerance"
  },
  {
    "id": "who-appointment",
    "type": "StructureDefinition",
    "url": "http://fhir.org/guides/who/core/StructureDefinition/who-appointment",
    "version": "0.1.0",
    "name": "WHOAppointment"
  },
  {
    "id": "who-careplan",
    "type": "StructureDefinition",
    "url": "http://fhir.org/guides/who/core/StructureDefinition/who-careplan",
    "version": "0.1.0",
    "name": "WHOCarePlan"
  },
  {
    "id": "who-careteam",
    "type": "StructureDefinition",
    "url": "http://fhir.org/guides/who/core/StructureDefinition/who-careteam",
    "version": "0.1.0",
    "name": "WHOCareTeam"
  },
  {
    "id": "who-condition",
    "type": "StructureDefinition",
    "url": "http://fhir.org/guides/who/core/StructureDefinition/who-condition",
    "version": "0.1.0",
    "name": "WHOCondition"
  },
  {
    "id": "who-doNotPerformReason",
    "type": "StructureDefinition",
    "url": "http://fhir.org/guides/who/core/StructureDefinition/who-doNotPerformReason",
    "version": "0.1.0",
    "name": "WHODoNotPerformReason"
  },
  {
    "id": "who-encounter",
    "type": "StructureDefinition",
    "url": "http://fhir.org/guides/who/core/StructureDefinition/who-encounter",
    "version": "0.1.0",
    "name": "WHOEncounter"
  },
  {
    "id": "who-episodeofcare",
    "type": "StructureDefinition",
    "url": "http://fhir.org/guides/who/core/StructureDefinition/who-episodeofcare",
    "version": "0.1.0",
    "name": "WHOEpisodeOfCare"
  },
  {
    "id": "who-group",
    "type": "StructureDefinition",
    "url": "http://fhir.org/guides/who/core/StructureDefinition/who-group",
    "version": "0.1.0",
    "name": "WHOGroup"
  },
  {
    "id": "who-groupdefinition",
    "type": "StructureDefinition",
    "url": "http://fhir.org/guides/who/core/StructureDefinition/who-groupdefinition",
    "version": "0.1.0",
    "name": "WHOGroupDefinition"
  },
  {
    "id": "who-immunization",
    "type": "StructureDefinition",
    "url": "http://fhir.org/guides/who/core/StructureDefinition/who-immunization",
    "version": "0.1.0",
    "name": "WHOImmunization"
  },
  {
    "id": "who-immunizationnotdone",
    "type": "StructureDefinition",
    "url": "http://fhir.org/guides/who/core/StructureDefinition/who-immunizationnotdone",
    "version": "0.1.0",
    "name": "WHOImmunizationNotDone"
  },
  {
    "id": "who-location",
    "type": "StructureDefinition",
    "url": "http://fhir.org/guides/who/core/StructureDefinition/who-location",
    "version": "0.1.0",
    "name": "WHOLocation"
  },
  {
    "id": "who-measurereport",
    "type": "StructureDefinition",
    "url": "http://fhir.org/guides/who/core/StructureDefinition/who-measurereport",
    "version": "0.1.0",
    "name": "WHOMeasureReport"
  },
  {
    "id": "who-medicationnotrequested",
    "type": "StructureDefinition",
    "url": "http://fhir.org/guides/who/core/StructureDefinition/who-medicationnotrequested",
    "version": "0.1.0",
    "name": "WHOMedicationNotRequested"
  },
  {
    "id": "who-medicationrequest",
    "type": "StructureDefinition",
    "url": "http://fhir.org/guides/who/core/StructureDefinition/who-medicationrequest",
    "version": "0.1.0",
    "name": "WHOMedicationRequest"
  },
  {
    "id": "who-notDone",
    "type": "StructureDefinition",
    "url": "http://fhir.org/guides/who/core/StructureDefinition/who-notDone",
    "version": "0.1.0",
    "name": "WHONotDone"
  },
  {
    "id": "who-notDoneReason",
    "type": "StructureDefinition",
    "url": "http://fhir.org/guides/who/core/StructureDefinition/who-notDoneReason",
    "version": "0.1.0",
    "name": "WHONotDoneReason"
  },
  {
    "id": "who-observation",
    "type": "StructureDefinition",
    "url": "http://fhir.org/guides/who/core/StructureDefinition/who-observation",
    "version": "0.1.0",
    "name": "WHOObservation"
  },
  {
    "id": "who-observationnotdone",
    "type": "StructureDefinition",
    "url": "http://fhir.org/guides/who/core/StructureDefinition/who-observationnotdone",
    "version": "0.1.0",
    "name": "WHOObservationNotDone"
  },
  {
    "id": "who-organization",
    "type": "StructureDefinition",
    "url": "http://fhir.org/guides/who/core/StructureDefinition/who-organization",
    "version": "0.1.0",
    "name": "WHOOrganization"
  },
  {
    "id": "who-patient",
    "type": "StructureDefinition",
    "url": "http://fhir.org/guides/who/core/StructureDefinition/who-patient",
    "version": "0.1.0",
    "name": "WHOPatient"
  },
  {
    "id": "who-practitioner",
    "type": "StructureDefinition",
    "url": "http://fhir.org/guides/who/core/StructureDefinition/who-practitioner",
    "version": "0.1.0",
    "name": "WHOPractitioner"
  },
  {
    "id": "who-practitionerrole",
    "type": "StructureDefinition",
    "url": "http://fhir.org/guides/who/core/StructureDefinition/who-practitionerrole",
    "version": "0.1.0",
    "name": "WHOPractitionerRole"
  },
  {
    "id": "who-procedure",
    "type": "StructureDefinition",
    "url": "http://fhir.org/guides/who/core/StructureDefinition/who-procedure",
    "version": "0.1.0",
    "name": "WHOProcedure"
  },
  {
    "id": "who-procedurenotdone",
    "type": "StructureDefinition",
    "url": "http://fhir.org/guides/who/core/StructureDefinition/who-procedurenotdone",
    "version": "0.1.0",
    "name": "WHOProcedureNotDone"
  },
  {
    "id": "who-relatedperson",
    "type": "StructureDefinition",
    "url": "http://fhir.org/guides/who/core/StructureDefinition/who-relatedperson",
    "version": "0.1.0",
    "name": "WHORelatedPerson"
  },
  {
    "id": "who-reportedLocation",
    "type": "StructureDefinition",
    "url": "http://fhir.org/guides/who/core/StructureDefinition/who-reportedLocation",
    "version": "0.1.0",
    "name": "WHOReportedLocation"
  },
  {
    "id": "who-servicenotrequested",
    "type": "StructureDefinition",
    "url": "http://fhir.org/guides/who/core/StructureDefinition/who-servicenotrequested",
    "version": "0.1.0",
    "name": "WHOServiceNotRequested"
  },
  {
    "id": "who-servicerequest",
    "type": "StructureDefinition",
    "url": "http://fhir.org/guides/who/core/StructureDefinition/who-servicerequest",
    "version": "0.1.0",
    "name": "WHOServiceRequest"
  },
  {
    "id": "emc-custom-codes-codes",
    "type": "CodeSystem",
    "url": "http://fhir.org/guides/who/emc-cds/CodeSystem/emc-custom-codes-codes",
    "version": "0.1.0",
    "name": "emc-custom-codes_codes"
  },
  {
    "id": "EmCareA",
    "type": "Questionnaire",
    "url": "http://fhir.org/guides/who/emc-cds/Questionnaire/EmCareA",
    "version": "0.1.0",
    "name": "EmCareA"
  },
  {
    "id": "EmCareB6",
    "type": "Questionnaire",
    "url": "http://fhir.org/guides/who/emc-cds/Questionnaire/EmCareB6",
    "version": "0.1.0",
    "name": "EmCareB6"
  },
  {
    "id": "EmCareB7",
    "type": "Questionnaire",
    "url": "http://fhir.org/guides/who/emc-cds/Questionnaire/EmCareB7",
    "version": "0.1.0",
    "name": "EmCareB7"
  },
  {
    "id": "birthdateestimator",
    "type": "StructureDefinition",
    "url": "http://fhir.org/guides/who/emc-cds/StructureDefinition/birthdateestimator",
    "version": "0.1.0",
    "name": "birthDateEstimator"
  },
  {
    "id": "emcare-a-de38",
    "type": "StructureDefinition",
    "url": "http://fhir.org/guides/who/emc-cds/StructureDefinition/emcare-a-de38",
    "version": "0.1.0",
    "name": "Caregiver wants to receive SMS or other messages regarding the child\u0027s visits and health status"
  },
  {
    "id": "emcare-communcationrequest",
    "type": "StructureDefinition",
    "url": "http://fhir.org/guides/who/emc-cds/StructureDefinition/emcare-communcationrequest",
    "version": "0.1.0",
    "name": "EmCare CommuncationRequest"
  },
  {
    "id": "emcare-device",
    "type": "StructureDefinition",
    "url": "http://fhir.org/guides/who/emc-cds/StructureDefinition/emcare-device",
    "version": "0.1.0",
    "name": "EmCare Device"
  },
  {
    "id": "emcare-encounter",
    "type": "StructureDefinition",
    "url": "http://fhir.org/guides/who/emc-cds/StructureDefinition/emcare-encounter",
    "version": "0.1.0",
    "name": "EmCare Encounter"
  },
  {
    "id": "emcare-observation",
    "type": "StructureDefinition",
    "url": "http://fhir.org/guides/who/emc-cds/StructureDefinition/emcare-observation",
    "version": "0.1.0",
    "name": "EmCare Observation"
  },
  {
    "id": "emcare-patient",
    "type": "StructureDefinition",
    "url": "http://fhir.org/guides/who/emc-cds/StructureDefinition/emcare-patient",
    "version": "0.1.0",
    "name": "EmCare Patient"
  },
  {
    "id": "emcare-relatedperson-caregiver",
    "type": "StructureDefinition",
    "url": "http://fhir.org/guides/who/emc-cds/StructureDefinition/emcare-relatedperson-caregiver",
    "version": "0.1.0",
    "name": "EmCare RelatedPerson Caregiver"
  },
  {
    "id": "emcare-relatedperson-father",
    "type": "StructureDefinition",
    "url": "http://fhir.org/guides/who/emc-cds/StructureDefinition/emcare-relatedperson-father",
    "version": "0.1.0",
    "name": "EmCare RelatedPerson Father"
  },
  {
    "id": "emcare-relatedperson-mother",
    "type": "StructureDefinition",
    "url": "http://fhir.org/guides/who/emc-cds/StructureDefinition/emcare-relatedperson-mother",
    "version": "0.1.0",
    "name": "EmCare RelatedPerson Mother"
  },
  {
    "id": "sms",
    "type": "StructureDefinition",
    "url": "http://fhir.org/guides/who/emc-cds/StructureDefinition/sms",
    "version": "0.1.0",
    "name": "sms"
  },
  {
    "id": "unknown",
    "type": "StructureDefinition",
    "url": "http://fhir.org/guides/who/emc-cds/StructureDefinition/unknown",
    "version": "0.1.0",
    "name": "unknown"
  },
  {
    "id": "vitalstatus",
    "type": "StructureDefinition",
    "url": "http://fhir.org/guides/who/emc-cds/StructureDefinition/vitalstatus",
    "version": "0.1.0",
    "name": "vitalStatus"
  },
  {
    "id": "emcare-a-de12",
    "type": "ValueSet",
    "url": "http://fhir.org/guides/who/emc-cds/ValueSet/emcare-a-de12",
    "version": "0.1.0",
    "name": "emcare-a-de12"
  },
  {
    "id": "emcare-a-de13",
    "type": "ValueSet",
    "url": "http://fhir.org/guides/who/emc-cds/ValueSet/emcare-a-de13",
    "version": "0.1.0",
    "name": "emcare-a-de13"
  },
  {
    "id": "emcare-a-de16",
    "type": "ValueSet",
    "url": "http://fhir.org/guides/who/emc-cds/ValueSet/emcare-a-de16",
    "version": "0.1.0",
    "name": "emcare-a-de16"
  },
  {
    "id": "emcare-a-de17",
    "type": "ValueSet",
    "url": "http://fhir.org/guides/who/emc-cds/ValueSet/emcare-a-de17",
    "version": "0.1.0",
    "name": "emcare-a-de17"
  },
  {
    "id": "emcare-a-de24",
    "type": "ValueSet",
    "url": "http://fhir.org/guides/who/emc-cds/ValueSet/emcare-a-de24",
    "version": "0.1.0",
    "name": "emcare-a-de24"
  },
  {
    "id": "emcare-a-de25",
    "type": "ValueSet",
    "url": "http://fhir.org/guides/who/emc-cds/ValueSet/emcare-a-de25",
    "version": "0.1.0",
    "name": "emcare-a-de25"
  },
  {
    "id": "emcare-a-de33",
    "type": "ValueSet",
    "url": "http://fhir.org/guides/who/emc-cds/ValueSet/emcare-a-de33",
    "version": "0.1.0",
    "name": "emcare-a-de33"
  },
  {
    "id": "emcare-a-de34",
    "type": "ValueSet",
    "url": "http://fhir.org/guides/who/emc-cds/ValueSet/emcare-a-de34",
    "version": "0.1.0",
    "name": "emcare-a-de34"
  },
  {
    "id": "emcare-a-de38",
    "type": "ValueSet",
    "url": "http://fhir.org/guides/who/emc-cds/ValueSet/emcare-a-de38",
    "version": "0.1.0",
    "name": "emcare-a-de38"
  },
  {
    "id": "emcare-a-de43",
    "type": "ValueSet",
    "url": "http://fhir.org/guides/who/emc-cds/ValueSet/emcare-a-de43",
    "version": "0.1.0",
    "name": "emcare-a-de43"
  },
  {
    "id": "emcare-a-de45",
    "type": "ValueSet",
    "url": "http://fhir.org/guides/who/emc-cds/ValueSet/emcare-a-de45",
    "version": "0.1.0",
    "name": "emcare-a-de45"
  },
  {
    "id": "emcare-b2-de01",
    "type": "ValueSet",
    "url": "http://fhir.org/guides/who/emc-cds/ValueSet/emcare-b2-de01",
    "version": "0.1.0",
    "name": "emcare-b2-de01"
  },
  {
    "id": "emcare-b2-de02",
    "type": "ValueSet",
    "url": "http://fhir.org/guides/who/emc-cds/ValueSet/emcare-b2-de02",
    "version": "0.1.0",
    "name": "emcare-b2-de02"
  },
  {
    "id": "emcare-b3-de01",
    "type": "ValueSet",
    "url": "http://fhir.org/guides/who/emc-cds/ValueSet/emcare-b3-de01",
    "version": "0.1.0",
    "name": "emcare-b3-de01"
  },
  {
    "id": "emcare-b3-de02",
    "type": "ValueSet",
    "url": "http://fhir.org/guides/who/emc-cds/ValueSet/emcare-b3-de02",
    "version": "0.1.0",
    "name": "emcare-b3-de02"
  },
  {
    "id": "emcare-b3-de05",
    "type": "ValueSet",
    "url": "http://fhir.org/guides/who/emc-cds/ValueSet/emcare-b3-de05",
    "version": "0.1.0",
    "name": "emcare-b3-de05"
  },
  {
    "id": "emcare-b3-de07",
    "type": "ValueSet",
    "url": "http://fhir.org/guides/who/emc-cds/ValueSet/emcare-b3-de07",
    "version": "0.1.0",
    "name": "emcare-b3-de07"
  },
  {
    "id": "emcare-b6-de19",
    "type": "ValueSet",
    "url": "http://fhir.org/guides/who/emc-cds/ValueSet/emcare-b6-de19",
    "version": "0.1.0",
    "name": "emcare-b6-de19"
  },
  {
    "id": "emcare-b7-de03",
    "type": "ValueSet",
    "url": "http://fhir.org/guides/who/emc-cds/ValueSet/emcare-b7-de03",
    "version": "0.1.0",
    "name": "emcare-b7-de03"
  },
  {
    "id": "emcare-b7-de04",
    "type": "ValueSet",
    "url": "http://fhir.org/guides/who/emc-cds/ValueSet/emcare-b7-de04",
    "version": "0.1.0",
    "name": "emcare-b7-de04"
  },
  {
    "id": "emcare-b7-de05",
    "type": "ValueSet",
    "url": "http://fhir.org/guides/who/emc-cds/ValueSet/emcare-b7-de05",
    "version": "0.1.0",
    "name": "emcare-b7-de05"
  },
  {
    "id": "emcare-b7-de10",
    "type": "ValueSet",
    "url": "http://fhir.org/guides/who/emc-cds/ValueSet/emcare-b7-de10",
    "version": "0.1.0",
    "name": "emcare-b7-de10"
  },
  {
    "id": "emcare-b7-de11",
    "type": "ValueSet",
    "url": "http://fhir.org/guides/who/emc-cds/ValueSet/emcare-b7-de11",
    "version": "0.1.0",
    "name": "emcare-b7-de11"
  },
  {
    "id": "emcare-b7-de14",
    "type": "ValueSet",
    "url": "http://fhir.org/guides/who/emc-cds/ValueSet/emcare-b7-de14",
    "version": "0.1.0",
    "name": "emcare-b7-de14"
  },
  {
    "id": "emcare-b7-de15",
    "type": "ValueSet",
    "url": "http://fhir.org/guides/who/emc-cds/ValueSet/emcare-b7-de15",
    "version": "0.1.0",
    "name": "emcare-b7-de15"
  },
  {
    "id": "who.fhir.emc-cds",
    "type": "ImplementationGuide",
    "url": "http://fhir.org/guides/who/emcare/ImplementationGuide/who.fhir.emc-cds",
    "version": "0.1.0",
    "name": "EMC-CDS"
  }
]