{
  "resourceType": "ValueSet",
  "id": "severe-impetigo-",
  "text": {
    "status": "generated",
    "div": "<div xmlns=\"http://www.w3.org/1999/xhtml\"><ul><li>Include these codes as defined in <code>https://fhir.dk.swisstph-mis.ch/matchbox/fhir/CodeSystem/codesystem-emcare-custom-codes</code><table class=\"none\"><tr><td style=\"white-space:nowrap\"><b>Code</b></td><td><b>Display</b></td></tr><tr><td>EmCare.B14S2.DE19</td><td>Skin Lesions ≥ 4 cm</td></tr><tr><td>EmCare.B14S2.DE20</td><td>Red Skin Streaks</td></tr><tr><td>EmCare.B14S2.DE21</td><td>Tender Nodes (Nodules) under the skin</td></tr><tr><td>EmCare.B14S2.DE22</td><td>Skin Infection extends to Muscle</td></tr><tr><td>EmCare.B14S2.DE23</td><td>Molluscum Contagiosum - Skin coloured pearly white papules with central umbilication. Most commonly seen on face and trunk in children.</td></tr><tr><td>EmCare.B14S2.DE24</td><td>Warts - Papules or nodules with a rough (Verrucous) surface</td></tr><tr><td>EmCare.B14S2.DE25</td><td>Seborrhea - Greasy scales and redness on central face and body folds</td></tr><tr><td>EmCare.B14S2.DE26</td><td>Fixed Drug Reactions - Generalised red, wide spread with small bumps or blisters; or one or more dark skin areas</td></tr><tr><td>EmCare.B14S2.DE27</td><td>Eczema - Wet oozing sores or excoriated, thick patches</td></tr><tr><td>EmCare.B14S2.DE28</td><td>Steven Johnson Syndrome - Severe reaction due to cotrimoxazole or NVP involving the skin as well as the eyes and the mouth.  Might cause difficulty in breathing</td></tr></table></li></ul></div>"
  },
  "url": "https://fhir.dk.swisstph-mis.ch/matchbox/fhir/ValueSet/valueset-severe-impetigo-",
  "version": "0.1.0",
  "name": "valueset-severe-impetigo-",
  "title": "Provide an estimated age or estimated date of birth",
  "status": "draft",
  "experimental": false,
  "date": "2022-05-02T16:42:45+00:00",
  "publisher": "World Health Organization (WHO)",
  "contact": [
    {
      "telecom": [
        {
          "system": "url",
          "value": "https://www.who.int"
        }
      ]
    }
  ],
  "description": "Codes representing possible values for the Provide an estimated age or estimated date of birth element",
  "jurisdiction": [
    {
      "coding": [
        {
          "system": "http://unstats.un.org/unsd/methods/m49/m49.htm",
          "code": "001"
        }
      ]
    }
  ],
  "immutable": true,
  "compose": {
    "include": [
      {
        "system": "https://fhir.dk.swisstph-mis.ch/matchbox/fhir/CodeSystem/codesystem-emcare-custom-codes",
        "concept": [
          {
            "code": "EmCare.B14S2.DE19",
            "display": "Skin Lesions ≥ 4 cm",
            "designation": [
              {
                "value": "The client has Skin Lesions ≥ 4 cm"
              }
            ]
          },
          {
            "code": "EmCare.B14S2.DE20",
            "display": "Red Skin Streaks",
            "designation": [
              {
                "value": "The client has red skin streaks"
              }
            ]
          },
          {
            "code": "EmCare.B14S2.DE21",
            "display": "Tender Nodes (Nodules) under the skin",
            "designation": [
              {
                "value": "The client has tender nodes (nodules) under the skin that can appear on any part of the face or body"
              }
            ]
          },
          {
            "code": "EmCare.B14S2.DE22",
            "display": "Skin Infection extends to Muscle",
            "designation": [
              {
                "value": "The client has skin infection that extends to muscle"
              }
            ]
          },
          {
            "code": "EmCare.B14S2.DE23",
            "display": "Molluscum Contagiosum - Skin coloured pearly white papules with central umbilication. Most commonly seen on face and trunk in children.",
            "designation": [
              {
                "value": "The client has Molluscum Contagiosum - Skin coloured pearly white papules with central umbilication. Most commonly seen on face and trunk in children."
              }
            ]
          },
          {
            "code": "EmCare.B14S2.DE24",
            "display": "Warts - Papules or nodules with a rough (Verrucous) surface",
            "designation": [
              {
                "value": "The client has Warts - Papules or nodules with a rough (Verrucous) surface"
              }
            ]
          },
          {
            "code": "EmCare.B14S2.DE25",
            "display": "Seborrhea - Greasy scales and redness on central face and body folds",
            "designation": [
              {
                "value": "The client has Seborrhea - Greasy scales and redness on central face and body folds"
              }
            ]
          },
          {
            "code": "EmCare.B14S2.DE26",
            "display": "Fixed Drug Reactions - Generalised red, wide spread with small bumps or blisters; or one or more dark skin areas",
            "designation": [
              {
                "value": "The client has Fixed Drug Reactions - Generalised red, wide spread with small bumps or blisters; or one or more dark skin areas"
              }
            ]
          },
          {
            "code": "EmCare.B14S2.DE27",
            "display": "Eczema - Wet oozing sores or excoriated, thick patches",
            "designation": [
              {
                "value": "The client has Eczema - Wet oozing sores or excoriated, thick patches"
              }
            ]
          },
          {
            "code": "EmCare.B14S2.DE28",
            "display": "Steven Johnson Syndrome - Severe reaction due to cotrimoxazole or NVP involving the skin as well as the eyes and the mouth.  Might cause difficulty in breathing",
            "designation": [
              {
                "value": "The client has Steven Johnson Syndrome - Severe reaction due to cotrimoxazole or NVP involving the skin as well as the eyes and the mouth.  Might cause difficulty in breathing"
              }
            ]
          }
        ]
      }
    ]
  }
}