{
  "resourceType": "ValueSet",
  "id": "emcare-a-de24",
  "url": "http://fhir.org/guides/who/emc-cds/ValueSet/emcare-a-de24",
  "name": "emcare-a-de24",
  "title": "Relationship to Client",
  "status": "draft",
  "experimental": false,
  "description": "Codes representing possible values for the Relationship to Client element",
  "immutable": true,
  "compose": {
    "include": [ {
      "system": "http://fhir.org/guides/who/emc-cds/CodeSystem/emc-custom-codes",
      "concept": [ {
        "code": "EmCare.A.DE24",
        "display": "Primary Caregiver's Relationship to Client"
      } ]
    } ]
  }
}