{
  "resourceType": "ValueSet",
  "id": "emcare-b7-de15",
  "url": "http://fhir.org/guides/who/emc-cds/ValueSet/emcare-b7-de15",
  "name": "emcare-b7-de15",
  "title": "Oral Fluid Test Choices",
  "status": "draft",
  "experimental": false,
  "description": "Codes representing possible values for the Oral Fluid Test Choices element",
  "immutable": true,
  "compose": {
    "include": [ {
      "system": "OralFluidTestResult",
      "concept": [ {
        "code": "everything",
        "display": "Vomits immediately / everything"
      }, {
        "code": "unable",
        "display": "Completely unable to drink"
      }, {
        "code": "poorly",
        "display": "Drinks poorly"
      } ]
    } ]
  }
}