{
    "resourceType": "ValueSet",
    "id": "child-vaccination-status",
    "url": "https://fhir.dk.swisstph-mis.ch/matchbox/fhir/ValueSet/child-vaccination-status",
    "name": "valueset-child-vaccination-status",
    "title": "EmCare.B17.DE45",
    "status": "draft",
    "experimental": false,
    "description": "Check the child's vaccination record: has the child received all vaccines they are eligible for",
    "immutable": true,
    "compose": {
        "include": [
            {
                "system": "https://fhir.dk.swisstph-mis.ch/matchbox/fhir/CodeSystem/emcare-custom-codes",
                "concept": [
                    {
                        "code": "EmCare.B17.DE46",
                        "display": "Yes",
                        "designation": [
                            {
                                "value": "The client has received all vaccinations for age"
                            }
                        ]
                    },
                    {
                        "code": "EmCare.B17.DE47",
                        "display": "No, incomplete vaccination",
                        "designation": [
                            {
                                "value": "The client has not received all vaccinations for age"
                            }
                        ]
                    },
                    {
                        "code": "EmCare.B17.DE48",
                        "display": "No, the child has never received any vaccinations to date",
                        "designation": [
                            {
                                "value": "The client has never received any vaccinations to date"
                            }
                        ]
                    },
                    {
                        "code": "EmCare.B17.DE49",
                        "display": "Unknown",
                        "designation": [
                            {
                                "value": "It is not known if the client has received any vaccination"
                            }
                        ]
                    }
                ]
            }
        ]
    }
}