{
  "resourceType": "StructureDefinition",
  "id": "unknown",
  "url": "http://fhir.org/guides/who/emc-cds/StructureDefinition/unknown",
  "name": "unknown",
  "title": "Child's Identity unknown/prefer to remain anonymous",
  "status": "draft",
  "experimental": false,
  "description": "The client's identity is unknown or the client's prefers to remain anonymous",
  "fhirVersion": "4.0.1",
  "kind": "complex-type",
  "abstract": false,
  "context": [ {
    "type": "element",
    "expression": "Patient"
  } ],
  "type": "Extension",
  "baseDefinition": "http://hl7.org/fhir/StructureDefinition/Extension",
  "derivation": "constraint",
  "differential": {
    "element": [ {
      "id": "Extension",
      "path": "Extension",
      "short": "Child's Identity unknown/prefer to remain anonymous",
      "definition": "The client's identity is unknown or the client's prefers to remain anonymous",
      "comment": "This field should only be used if the client has identity concerns - Should this be the case then a  Unique Identification EMCare.A.DE02 should be used to auto generate a unique ID - the only required fields to be completed would then be age and sex.  All other fields will become optional for the registration.",
      "min": 0,
      "max": "1"
    }, {
      "id": "Extension.extension",
      "path": "Extension.extension",
      "min": 0,
      "max": "1"
    }, {
      "id": "Extension.url",
      "path": "Extension.url",
      "fixedUri": "http://fhir.org/guides/who/emc-cds/StructureDefinition/unknown"
    }, {
      "id": "Extension.value[x]",
      "path": "Extension.value[x]",
      "short": "Child's Identity unknown/prefer to remain anonymous",
      "definition": "The client's identity is unknown or the client's prefers to remain anonymous",
      "min": 1,
      "type": [ {
        "code": "boolean"
      } ]
    } ]
  }
}